{
    "tags": [],
    "strength": "18",
    "dexterity": "14",
    "constitution": "15",
    "intelligence": "11",
    "wisdom": "17",
    "charisma": "16",
    "name": "Corrupted Avatar of Lurue",
    "AC": 14,
    "speed": [
        "50 ft",
        "fly 50 ft. (hover)"
    ],
    "saving_throws": {
        "intelligence": "proficient",
        "wisdom": "proficient",
        "charisma": "proficient"
    },
    "skills": {},
    "damage_immunities": [
        "poison"
    ],
    "condition_immunities": [
        "charmed, paralyzed, poisoned"
    ],
    "senses": [
        "darkvision 60 ft.",
        "passive Perception 13"
    ],
    "languages": [
        "Celestial",
        "Elvish",
        "Sylvan",
        "telepathy 60 ft."
    ],
    "CR": "8 (3,900 XP)",
    "page": 123,
    "book": "Candlekeep Mysteries",
    "actions": {}
}