{
    "tags": [],
    "strength": "12",
    "dexterity": "21",
    "constitution": "16",
    "intelligence": "19",
    "wisdom": "10",
    "charisma": "14",
    "insight": "+4",
    "perception": "+4",
    "name": "Hydroloth",
    "AC": 15,
    "speed": [
        "20 ft",
        "swim 40 ft"
    ],
    "saving_throws": {},
    "skills": {
        "insight": "proficient",
        "perception": "proficient"
    },
    "damage_immunities": [
        "acid, poison"
    ],
    "resistances": [
        "cold, lightning",
        "bludgeoning, piercing, and slashing from nonmagical attacks"
    ],
    "condition_immunities": [
        "poisoned"
    ],
    "senses": [
        "blindsight 60 ft.",
        "darkvision 60 ft.",
        "passive Perception 14"
    ],
    "languages": [
        "Abyssal",
        "Infernal",
        "telepathy 60 ft."
    ],
    "CR": "9 (5,000 XP)",
    "page": 249,
    "book": "Mordenkainen\\xe2\\x80\\x99s Tome of Foes",
    "traits": {
        "Amphibious": "The hydroloth can breathe air and water.",
        "spellcasting": {
            "type": "innate",
            "spells": [
                "darkness",
                "detect magic",
                "dispel magic",
                "invisibility",
                "water walk",
                "control water",
                "crown of madness",
                "fear",
                "phantasmal killer",
                "suggestion"
            ]
        },
        "Magic Resistance": "The hydroloth has advantage on saving throws against spells and other magical effects.",
        "Magic Weapons": "The hydroloth's weapon attacks are magical.",
        "Secure Memory": "The hydroloth is immune to the waters of the River Styx as well as any effect that would steal or modify its memories or detect or read its thoughts.",
        "Watery Advantage": "While submerged in liquid, the hydroloth has advantage on attack rolls."
    },
    "actions": {}
}