{
    "tags": [],
    "hit": "7d8",
    "strength": "12",
    "dexterity": "16",
    "constitution": "11",
    "intelligence": "12",
    "wisdom": "10",
    "charisma": "14",
    "perception": "+2",
    "performance": "+6",
    "stealth": "+5",
    "name": "Satyr",
    "AC": 14,
    "speed": [
        "40 ft"
    ],
    "saving_throws": {},
    "skills": {
        "perception": "proficient",
        "performance": "expert",
        "stealth": "proficient"
    },
    "senses": [
        "passive Perception 12"
    ],
    "languages": [
        "Common",
        "Elvish",
        "Sylvan"
    ],
    "CR": "1/2 (100 XP)",
    "page": 267,
    "book": "Monster Manual",
    "traits": {
        "Magic Resistance": "The satyr has advantage on saving throws against spells and other magical effects."
    },
    "actions": {}
}