{
    "tags": [],
    "hit points": "6d8 + 12",
    "strength": "15 (+2)",
    "dexterity": "16 (+3)",
    "constitution": "15 (+2)",
    "intelligence": "7 (-2)",
    "wisdom": "12 (+1)",
    "charisma": "8 (-1)",
    "name": "Adult Kruthik",
    "AC": 18,
    "speed": [
        "40 ft",
        "burrow 20 ft",
        "climb 40 ft"
    ],
    "saving_throws": {},
    "skills": {},
    "senses": [
        "darkvision 60 ft.",
        "tremorsense 60 ft.",
        "passive Perception 11"
    ],
    "languages": [
        "Kruthik"
    ],
    "CR": "variable",
    "page": 212,
    "book": "Mordenkainen\u2019s Tome of Foes",
    "traits": {
        "Keen Smell": "The kruthik has advantage on Wisdom (Perception) checks that rely on smell.",
        "Pack Tactics": "The kruthik has advantage on an attack roll against a creature if at least one of the kruthik's allies is within 5 feet of the creature and the ally isn't incapacitated.",
        "Tunneler": "The kruthik can burrow through solid rock at half its burrowing speed and leaves a 5-foot-diameter tunnel in its wake."
    },
    "actions": {
        "Multiattack": "The kruthik makes two stab attacks or two spike attacks.",
        "Stab": "Melee Weapon Attack: +5+1d4 + 3 to hit, reach 5 ft., one target. Hit: 6 (1d6 + 3) piercing damage.",
        "Spike": "Ranged Weapon Attack: +5+1d4 + 3 to hit, range 20/60 ft., one target. Hit: 5 (1d4 + 3) piercing damage."
    },
    "legendary_actions": {
        "number": 0,
        "options": {}
    },
    "alignment": "U",
    "size": "Medium",
    "type": "monstrosity"
}