{
    "tags": [],
    "hit points": "4d10 + 16",
    "strength": "20 (+5)",
    "dexterity": "10 (+0)",
    "constitution": "19 (+4)",
    "intelligence": "2 (-4)",
    "wisdom": "12 (+1)",
    "charisma": "5 (-3)",
    "name": "Aurochs",
    "HP": "38 (4d10 + 16)",
    "AC": 11,
    "speed": [
        "50 ft"
    ],
    "saving_throws": {},
    "skills": {},
    "senses": [
        "passive Perception 11"
    ],
    "languages": [
        "\u2014"
    ],
    "CR": "2 (450 XP)",
    "page": 207,
    "book": "Volo\u2019s Guide to Monsters",
    "traits": {
        "Charge": "If the aurochs moves at least 20 feet straight toward a target and then hits it with a gore attack on the same turn, the target takes an extra 9 (2d8) piercing damage. If the target is a creature, it must succeed on a DC 15+1d4 + 13 Strength saving throw or be knocked prone."
    },
    "actions": {
        "Gore": "Melee Weapon Attack: +7+1d4 + 5 to hit, reach 5 ft., one target. Hit: 14 (2d8 + 5) piercing damage."
    },
    "alignment": "U",
    "size": "Large",
    "type": "beast"
}