{
    "tags": [],
    "hit": "1d4",
    "strength": "2",
    "dexterity": "14",
    "constitution": "10",
    "intelligence": "4",
    "wisdom": "11",
    "charisma": "8",
    "name": "Cranium Rat",
    "page": 133,
    "book": "Volo\\xe2\\x80\\x99s Guide to Monsters",
    "alignment": "LE",
    "size": "Tiny",
    "type": "beast",
    "AC": 12,
    "speed": [
        "30 ft"
    ],
    "saving_throws": {},
    "skills": {},
    "senses": [
        "darkvision 30 ft.",
        "passive Perception 10"
    ],
    "languages": [
        "telepathy 30 ft."
    ],
    "CR": "0 (0 or 10 XP)"
}