{
    "tags": [
        "elf"
    ],
    "hit": "10d8",
    "strength": "9",
    "dexterity": "14",
    "constitution": "10",
    "intelligence": "17",
    "wisdom": "13",
    "charisma": "12",
    "arcana": "+6",
    "deception": "+4",
    "perception": "+4",
    "stealth": "+5",
    "name": "Drow Mage",
    "HP": "45 (10d8)",
    "AC": 12,
    "speed": [
        "30 ft"
    ],
    "saving_throws": {},
    "skills": {
        "arcana": "proficient",
        "deception": "proficient",
        "perception": "proficient",
        "stealth": "proficient"
    },
    "senses": [
        "darkvision 120 ft.",
        "passive Perception 14"
    ],
    "languages": [
        "Elvish",
        "Undercommon"
    ],
    "CR": "7 (2,900 XP)",
    "page": 129,
    "book": "Monster Manual",
    "traits": {
        "Fey Ancestry": "The drow has advantage on saving throws against being charmed, and magic can't put the drow to sleep.",
        "spellcasting": {
            "ability": "intelligence",
            "type": "innate",
            "spells": {
                "Cantrips": [
                    "mage hand",
                    "minor illusion",
                    "poison spray",
                    "ray of frost"
                ],
                "1st": [
                    "mage armor",
                    "magic missile",
                    "shield",
                    "witch bolt"
                ],
                "2nd": [
                    "alter self",
                    "misty step",
                    "web"
                ],
                "3rd": [
                    "fly",
                    "lightning bolt"
                ],
                "4th": [
                    "Evard\\'s black tentacles",
                    "greater invisibility"
                ],
                "5th": [
                    "cloudkill"
                ]
            }
        },
        "Sunlight Sensitivity": "While in sunlight, the drow has disadvantage on attack rolls, as well as on Wisdom (Perception) checks that rely on sight."
    },
    "actions": {
        "Staff": "Melee Weapon Attack: +2+1d6 - 1 to hit, reach 5 ft., one target. Hit: 2 (1d6 - 1) bludgeoning damage, or 3 (1d8 - 1) bludgeoning damage if used with two hands, plus 3 (1d6) poison damage.",
        "Summon Demon (1/Day)": "The drow magically summons a quasit, or attempts to summon a shadow demon with a 50 percent chance of success. The summoned demon appears in an unoccupied space within 60 feet of its summoner, acts as an ally of its summoner, and can't summon other demons. It remains for 10 minutes, until it or its summoner dies, or until its summoner dismisses it as an action."
    },
    "alignment": "NE",
    "size": "Medium",
    "type": "humanoid"
}