{
    "tags": [
        "gnoll"
    ],
    "strength": "16",
    "dexterity": "14",
    "constitution": "13",
    "intelligence": "8",
    "wisdom": "11",
    "charisma": "9",
    "name": "Gnoll Pack Lord",
    "AC": 15,
    "speed": [
        "30 ft"
    ],
    "saving_throws": {},
    "skills": {},
    "senses": [
        "darkvision 60 ft.",
        "passive Perception 10"
    ],
    "languages": [
        "Gnoll"
    ],
    "CR": "2 (450 XP)",
    "page": 163,
    "book": "Monster Manual",
    "traits": {
        "Rampage": "When the gnoll reduces a creature to 0 hit points with a melee attack on its turn, the gnoll can take a bonus action to move up to half its speed and make a bite attack."
    },
    "actions": {},
    "legendary_actions": {
        "number": 0,
        "options": {}
    },
    "alignment": "CE",
    "size": "Medium",
    "type": "humanoid"
}