{
    "tags": [
        "kraul"
    ],
    "strength": "16",
    "dexterity": "12",
    "constitution": "14",
    "intelligence": "12",
    "wisdom": "15",
    "charisma": "10",
    "insight": "+4",
    "nature": "+3",
    "religion": "+3",
    "name": "Kraul Death Priest",
    "AC": 18,
    "speed": [
        "30 ft",
        "climb 30 ft",
        "fly 40 ft"
    ],
    "saving_throws": {
        "constitution": "proficient",
        "wisdom": "proficient"
    },
    "skills": {
        "insight": "proficient",
        "nature": "proficient",
        "religion": "proficient"
    },
    "senses": [
        "darkvision 60 ft.",
        "passive Perception 12"
    ],
    "languages": [
        "Common",
        "Kraul"
    ],
    "CR": "4 (1,100 XP)",
    "page": 214,
    "book": "Guildmasters\\xe2\\x80\\x99 Guide to Ravnica",
    "traits": {
        "Feed on Death": "When a creature within 30 feet of the kraul drops to 0 hit points, the kraul or another creature of its choice within 30 feet of it gains 5 (1d10) temporary hit points, provided the kraul isn't incapacitated.",
        "Hive Mind": "The kraul is immune to the charmed and frightened conditions while within 30 feet of at least one other kraul.",
        "spellcasting": {
            "type": "innate",
            "spells": [
                "chill touch",
                "poison spray",
                "ray of enfeeblement",
                "ray of sickness",
                "animate dead",
                "blight",
                "vampiric touch"
            ]
        },
        "Pack Tactics": "The kraul has advantage on an attack roll against a creature if at least one of the kraul's allies is within 5 feet of the creature and the ally isn't incapacitated.",
        "Spider Climb": "The kraul can climb difficult surfaces, including upside down on ceilings, without needing to make an ability check."
    },
    "alignment": "NE",
    "size": "Medium",
    "type": "humanoid"
}