{
    "tags": [],
    "strength": "26",
    "dexterity": "10",
    "constitution": "20",
    "intelligence": "1",
    "wisdom": "10",
    "charisma": "1",
    "perception": "+2",
    "stealth": "+2",
    "name": "Living Bigby\\'s Hand",
    "HP": "52 (5d10 + 25)",
    "AC": 20,
    "speed": [
        "0 ft",
        "fly 60 ft. (hover)"
    ],
    "saving_throws": {
        "dexterity": "proficient",
        "wisdom": "proficient"
    },
    "skills": {
        "perception": "proficient",
        "stealth": "proficient"
    },
    "damage_immunities": [
        "poison"
    ],
    "condition_immunities": [
        "blinded, charmed, deafened, exhaustion, frightened, paralyzed, petrified, poisoned, unconscious"
    ],
    "senses": [
        "darkvision 60 ft.",
        "passive Perception 12"
    ],
    "languages": [
        "\\xe2\\x80\\x94"
    ],
    "CR": "4 (1,100 XP)",
    "page": 298,
    "book": "Icewind Dale: Rime of the Frostmaiden",
    "traits": {
        "Magic Resistance": "The living spell has advantage on saving throws against spells and other magical effects.",
        "Unusual Nature": "The living spell doesn't require air, food, drink, or sleep."
    },
    "actions": {
        "Force Fist": "Melee Spell Attack: +10+1d4 + 8 to hit, reach 5 ft., one target. Hit: 26 (4d8 + 8) force damage. If the target is a Large or smaller creature, the living spell can move it up to 5 feet and move with it, without provoking opportunity attacks.",
        "Grasping Hand": "The living spell attempts to grab a Huge or smaller creature within 5 feet of it. The target must succeed on a DC 15+1d4 + 13 Dexterity saving throw or be grappled (escape DC 15+1d4 + 13). Until the grapple ends, the target takes 15 (2d6 + 8) bludgeoning damage at the start of each of its turns. The living spell can grapple only one creature at a time and can't use Force Fist until the grapple ends."
    },
    "alignment": "U",
    "size": "Large",
    "type": "construct"
}