{
    "tags": [],
    "hit": "7d8",
    "strength": "12",
    "dexterity": "16",
    "constitution": "11",
    "intelligence": "12",
    "wisdom": "10",
    "charisma": "14",
    "perception": "+2",
    "performance": "+6",
    "stealth": "+5",
    "name": "Satyr",
    "AC": 14,
    "speed": [
        "40 ft"
    ],
    "saving_throws": {},
    "skills": {
        "perception": "proficient",
        "performance": "expert",
        "stealth": "proficient"
    },
    "senses": [
        "passive Perception 12"
    ],
    "languages": [
        "Common",
        "Elvish",
        "Sylvan"
    ],
    "CR": "1/2 (100 XP)",
    "page": 267,
    "book": "Monster Manual",
    "traits": {
        "Magic Resistance": "The satyr has advantage on saving throws against spells and other magical effects."
    },
    "actions": {
        "Ram": "Melee Weapon Attack: +3+1d4 + 1 to hit, reach 5 ft., one target. Hit: 6 (2d4 + 1) bludgeoning damage.",
        "Shortsword": "Melee Weapon Attack: +5+1d4 + 3 to hit, reach 5 ft., one target. Hit: 6 (1d6 + 3) piercing damage.",
        "Shortbow": "Ranged Weapon Attack: +5+1d4 + 3 to hit, range 80/320 ft., one target. Hit: 6 (1d6 + 3) piercing damage."
    },
    "legendary_actions": {
        "number": 0,
        "options": {}
    },
    "alignment": "CN",
    "size": "Medium",
    "type": "fey"
}